[{"Radius":100.0,"Name":"Circle","OutputMessage":"A circle with radius: 100","ShapePrinter":{}},{"Height":100.0,"Width":200.0,"Name":"Rectangle","OutputMessage":"A rectangle with height 100 and width 200","ShapePrinter":{}},{"Side1":33.0,"Side2":44.0,"Side3":55.0,"Name":"Triangle","OutputMessage":"A triangle with sides 33, 44, 55","ShapePrinter":{}},{"Radius":100.0,"Name":"Circle","OutputMessage":"A circle with radius: 100","ShapePrinter":{}},{"Height":100.0,"Width":200.0,"Name":"Rectangle","OutputMessage":"A rectangle with height 100 and width 200","ShapePrinter":{}},{"Side1":33.0,"Side2":44.0,"Side3":55.0,"Name":"Triangle","OutputMessage":"A triangle with sides 33, 44, 55","ShapePrinter":{}}]